package com.inmobi.androidsdk;

import android.os.Handler;
import java.lang.ref.WeakReference;

class InterstitialView$c
  extends Handler
{
  private final WeakReference<InterstitialView> a;
  
  public InterstitialView$c(InterstitialView paramInterstitialView)
  {
    a = new WeakReference(paramInterstitialView);
  }
  
  /* Error */
  public void handleMessage(android.os.Message paramMessage)
  {
    // Byte code:
    //   0: aload_0
    //   1: getfield 19	com/inmobi/androidsdk/InterstitialView$c:a	Ljava/lang/ref/WeakReference;
    //   4: invokevirtual 30	java/lang/ref/WeakReference:get	()Ljava/lang/Object;
    //   7: checkcast 32	com/inmobi/androidsdk/InterstitialView
    //   10: astore_2
    //   11: aload_2
    //   12: ifnull +796 -> 808
    //   15: aload_1
    //   16: getfield 38	android/os/Message:what	I
    //   19: tableswitch	default:+789->808, 303:+634->653, 304:+751->770, 305:+773->792, 306:+505->524, 307:+353->372, 308:+45->64, 309:+286->305, 310:+315->334
    //   64: invokestatic 44	java/lang/System:currentTimeMillis	()J
    //   67: aload_2
    //   68: invokestatic 48	com/inmobi/androidsdk/InterstitialView:c	(Lcom/inmobi/androidsdk/InterstitialView;)J
    //   71: lsub
    //   72: lstore 4
    //   74: aload_2
    //   75: invokestatic 52	com/inmobi/androidsdk/InterstitialView:d	(Lcom/inmobi/androidsdk/InterstitialView;)Z
    //   78: ifeq +48 -> 126
    //   81: new 54	org/json/JSONObject
    //   84: dup
    //   85: invokespecial 55	org/json/JSONObject:<init>	()V
    //   88: astore_1
    //   89: aload_1
    //   90: ldc 57
    //   92: aload_2
    //   93: invokestatic 61	com/inmobi/androidsdk/InterstitialView:e	(Lcom/inmobi/androidsdk/InterstitialView;)Ljava/lang/String;
    //   96: invokevirtual 65	org/json/JSONObject:put	(Ljava/lang/String;Ljava/lang/Object;)Lorg/json/JSONObject;
    //   99: pop
    //   100: aload_1
    //   101: ldc 67
    //   103: lload 4
    //   105: invokevirtual 70	org/json/JSONObject:put	(Ljava/lang/String;J)Lorg/json/JSONObject;
    //   108: pop
    //   109: invokestatic 76	com/inmobi/androidsdk/bootstrapper/Initializer:getLogger	()Lcom/inmobi/commons/metric/Logger;
    //   112: new 78	com/inmobi/commons/metric/EventLog
    //   115: dup
    //   116: getstatic 84	com/inmobi/androidsdk/bootstrapper/NetworkEventType:FETCH_COMPLETE	Lcom/inmobi/androidsdk/bootstrapper/NetworkEventType;
    //   119: aload_1
    //   120: invokespecial 87	com/inmobi/commons/metric/EventLog:<init>	(Lcom/inmobi/commons/metric/EventType;Lorg/json/JSONObject;)V
    //   123: invokevirtual 93	com/inmobi/commons/metric/Logger:logEvent	(Lcom/inmobi/commons/metric/EventLog;)V
    //   126: aload_0
    //   127: sipush 306
    //   130: invokevirtual 97	com/inmobi/androidsdk/InterstitialView$c:removeMessages	(I)V
    //   133: aload_2
    //   134: invokestatic 101	com/inmobi/androidsdk/InterstitialView:f	(Lcom/inmobi/androidsdk/InterstitialView;)Lcom/inmobi/re/container/IMWebView;
    //   137: ifnonnull +59 -> 196
    //   140: aload_2
    //   141: new 103	com/inmobi/re/container/IMWebView
    //   144: dup
    //   145: aload_2
    //   146: invokestatic 107	com/inmobi/androidsdk/InterstitialView:g	(Lcom/inmobi/androidsdk/InterstitialView;)Landroid/app/Activity;
    //   149: aload_2
    //   150: invokestatic 111	com/inmobi/androidsdk/InterstitialView:h	(Lcom/inmobi/androidsdk/InterstitialView;)Lcom/inmobi/re/container/IMWebView$IMWebViewListener;
    //   153: iconst_1
    //   154: iconst_0
    //   155: invokespecial 114	com/inmobi/re/container/IMWebView:<init>	(Landroid/content/Context;Lcom/inmobi/re/container/IMWebView$IMWebViewListener;ZZ)V
    //   158: invokestatic 117	com/inmobi/androidsdk/InterstitialView:a	(Lcom/inmobi/androidsdk/InterstitialView;Lcom/inmobi/re/container/IMWebView;)Lcom/inmobi/re/container/IMWebView;
    //   161: pop
    //   162: aload_2
    //   163: getfield 121	com/inmobi/androidsdk/InterstitialView:b	Z
    //   166: ifne +10 -> 176
    //   169: aload_2
    //   170: invokestatic 101	com/inmobi/androidsdk/InterstitialView:f	(Lcom/inmobi/androidsdk/InterstitialView;)Lcom/inmobi/re/container/IMWebView;
    //   173: invokevirtual 124	com/inmobi/re/container/IMWebView:disableHardwareAcceleration	()V
    //   176: aload_2
    //   177: invokestatic 101	com/inmobi/androidsdk/InterstitialView:f	(Lcom/inmobi/androidsdk/InterstitialView;)Lcom/inmobi/re/container/IMWebView;
    //   180: new 126	com/inmobi/androidsdk/impl/imai/IMAIController
    //   183: dup
    //   184: aload_2
    //   185: invokestatic 101	com/inmobi/androidsdk/InterstitialView:f	(Lcom/inmobi/androidsdk/InterstitialView;)Lcom/inmobi/re/container/IMWebView;
    //   188: invokespecial 129	com/inmobi/androidsdk/impl/imai/IMAIController:<init>	(Lcom/inmobi/re/container/IMWebView;)V
    //   191: ldc -125
    //   193: invokevirtual 135	com/inmobi/re/container/IMWebView:addJavascriptInterface	(Ljava/lang/Object;Ljava/lang/String;)V
    //   196: aload_2
    //   197: invokestatic 138	com/inmobi/androidsdk/InterstitialView:i	(Lcom/inmobi/androidsdk/InterstitialView;)Ljava/lang/String;
    //   200: ifnull +32 -> 232
    //   203: aload_2
    //   204: aload_2
    //   205: invokestatic 138	com/inmobi/androidsdk/InterstitialView:i	(Lcom/inmobi/androidsdk/InterstitialView;)Ljava/lang/String;
    //   208: ldc -116
    //   210: new 142	java/lang/StringBuilder
    //   213: dup
    //   214: invokespecial 143	java/lang/StringBuilder:<init>	()V
    //   217: lload 4
    //   219: invokevirtual 147	java/lang/StringBuilder:append	(J)Ljava/lang/StringBuilder;
    //   222: invokevirtual 151	java/lang/StringBuilder:toString	()Ljava/lang/String;
    //   225: invokevirtual 157	java/lang/String:replace	(Ljava/lang/CharSequence;Ljava/lang/CharSequence;)Ljava/lang/String;
    //   228: invokestatic 160	com/inmobi/androidsdk/InterstitialView:a	(Lcom/inmobi/androidsdk/InterstitialView;Ljava/lang/String;)Ljava/lang/String;
    //   231: pop
    //   232: aload_2
    //   233: aload_2
    //   234: invokestatic 138	com/inmobi/androidsdk/InterstitialView:i	(Lcom/inmobi/androidsdk/InterstitialView;)Ljava/lang/String;
    //   237: invokestatic 163	com/inmobi/androidsdk/InterstitialView:c	(Lcom/inmobi/androidsdk/InterstitialView;Ljava/lang/String;)V
    //   240: return
    //   241: astore_1
    //   242: ldc -91
    //   244: ldc -89
    //   246: aload_1
    //   247: invokestatic 173	com/inmobi/commons/internal/Log:debug	(Ljava/lang/String;Ljava/lang/String;Ljava/lang/Throwable;)V
    //   250: aload_2
    //   251: getstatic 179	com/inmobi/androidsdk/InterstitialView$State:INIT	Lcom/inmobi/androidsdk/InterstitialView$State;
    //   254: invokestatic 182	com/inmobi/androidsdk/InterstitialView:a	(Lcom/inmobi/androidsdk/InterstitialView;Lcom/inmobi/androidsdk/InterstitialView$State;)Lcom/inmobi/androidsdk/InterstitialView$State;
    //   257: pop
    //   258: aload_2
    //   259: bipush 101
    //   261: getstatic 188	com/inmobi/androidsdk/AdRequest$ErrorCode:INTERNAL_ERROR	Lcom/inmobi/androidsdk/AdRequest$ErrorCode;
    //   264: invokestatic 191	com/inmobi/androidsdk/InterstitialView:a	(Lcom/inmobi/androidsdk/InterstitialView;ILcom/inmobi/androidsdk/AdRequest$ErrorCode;)V
    //   267: return
    //   268: astore_1
    //   269: ldc -91
    //   271: ldc -63
    //   273: aload_1
    //   274: invokestatic 196	com/inmobi/commons/internal/Log:internal	(Ljava/lang/String;Ljava/lang/String;Ljava/lang/Throwable;)V
    //   277: return
    //   278: astore_3
    //   279: ldc -91
    //   281: new 142	java/lang/StringBuilder
    //   284: dup
    //   285: ldc -58
    //   287: invokespecial 201	java/lang/StringBuilder:<init>	(Ljava/lang/String;)V
    //   290: invokestatic 44	java/lang/System:currentTimeMillis	()J
    //   293: invokevirtual 147	java/lang/StringBuilder:append	(J)Ljava/lang/StringBuilder;
    //   296: invokevirtual 151	java/lang/StringBuilder:toString	()Ljava/lang/String;
    //   299: invokestatic 204	com/inmobi/commons/internal/Log:internal	(Ljava/lang/String;Ljava/lang/String;)V
    //   302: goto -193 -> 109
    //   305: aload_0
    //   306: sipush 306
    //   309: invokevirtual 97	com/inmobi/androidsdk/InterstitialView$c:removeMessages	(I)V
    //   312: aload_2
    //   313: getstatic 179	com/inmobi/androidsdk/InterstitialView$State:INIT	Lcom/inmobi/androidsdk/InterstitialView$State;
    //   316: invokestatic 182	com/inmobi/androidsdk/InterstitialView:a	(Lcom/inmobi/androidsdk/InterstitialView;Lcom/inmobi/androidsdk/InterstitialView$State;)Lcom/inmobi/androidsdk/InterstitialView$State;
    //   319: pop
    //   320: aload_2
    //   321: bipush 101
    //   323: aload_1
    //   324: getfield 208	android/os/Message:obj	Ljava/lang/Object;
    //   327: checkcast 184	com/inmobi/androidsdk/AdRequest$ErrorCode
    //   330: invokestatic 191	com/inmobi/androidsdk/InterstitialView:a	(Lcom/inmobi/androidsdk/InterstitialView;ILcom/inmobi/androidsdk/AdRequest$ErrorCode;)V
    //   333: return
    //   334: aload_0
    //   335: sipush 307
    //   338: invokevirtual 97	com/inmobi/androidsdk/InterstitialView$c:removeMessages	(I)V
    //   341: aload_0
    //   342: sipush 303
    //   345: invokevirtual 97	com/inmobi/androidsdk/InterstitialView$c:removeMessages	(I)V
    //   348: aload_2
    //   349: getstatic 179	com/inmobi/androidsdk/InterstitialView$State:INIT	Lcom/inmobi/androidsdk/InterstitialView$State;
    //   352: invokestatic 182	com/inmobi/androidsdk/InterstitialView:a	(Lcom/inmobi/androidsdk/InterstitialView;Lcom/inmobi/androidsdk/InterstitialView$State;)Lcom/inmobi/androidsdk/InterstitialView$State;
    //   355: pop
    //   356: aload_2
    //   357: aconst_null
    //   358: invokestatic 117	com/inmobi/androidsdk/InterstitialView:a	(Lcom/inmobi/androidsdk/InterstitialView;Lcom/inmobi/re/container/IMWebView;)Lcom/inmobi/re/container/IMWebView;
    //   361: pop
    //   362: aload_2
    //   363: bipush 101
    //   365: getstatic 188	com/inmobi/androidsdk/AdRequest$ErrorCode:INTERNAL_ERROR	Lcom/inmobi/androidsdk/AdRequest$ErrorCode;
    //   368: invokestatic 191	com/inmobi/androidsdk/InterstitialView:a	(Lcom/inmobi/androidsdk/InterstitialView;ILcom/inmobi/androidsdk/AdRequest$ErrorCode;)V
    //   371: return
    //   372: aload_0
    //   373: sipush 310
    //   376: invokevirtual 97	com/inmobi/androidsdk/InterstitialView$c:removeMessages	(I)V
    //   379: aload_0
    //   380: sipush 303
    //   383: invokevirtual 97	com/inmobi/androidsdk/InterstitialView$c:removeMessages	(I)V
    //   386: aload_2
    //   387: getstatic 179	com/inmobi/androidsdk/InterstitialView$State:INIT	Lcom/inmobi/androidsdk/InterstitialView$State;
    //   390: invokestatic 182	com/inmobi/androidsdk/InterstitialView:a	(Lcom/inmobi/androidsdk/InterstitialView;Lcom/inmobi/androidsdk/InterstitialView$State;)Lcom/inmobi/androidsdk/InterstitialView$State;
    //   393: pop
    //   394: aload_2
    //   395: invokestatic 101	com/inmobi/androidsdk/InterstitialView:f	(Lcom/inmobi/androidsdk/InterstitialView;)Lcom/inmobi/re/container/IMWebView;
    //   398: invokevirtual 211	com/inmobi/re/container/IMWebView:cancelLoad	()V
    //   401: aload_2
    //   402: invokestatic 101	com/inmobi/androidsdk/InterstitialView:f	(Lcom/inmobi/androidsdk/InterstitialView;)Lcom/inmobi/re/container/IMWebView;
    //   405: invokevirtual 214	com/inmobi/re/container/IMWebView:stopLoading	()V
    //   408: aload_2
    //   409: invokestatic 101	com/inmobi/androidsdk/InterstitialView:f	(Lcom/inmobi/androidsdk/InterstitialView;)Lcom/inmobi/re/container/IMWebView;
    //   412: invokevirtual 217	com/inmobi/re/container/IMWebView:deinit	()V
    //   415: aload_2
    //   416: aconst_null
    //   417: invokestatic 117	com/inmobi/androidsdk/InterstitialView:a	(Lcom/inmobi/androidsdk/InterstitialView;Lcom/inmobi/re/container/IMWebView;)Lcom/inmobi/re/container/IMWebView;
    //   420: pop
    //   421: aload_2
    //   422: invokestatic 52	com/inmobi/androidsdk/InterstitialView:d	(Lcom/inmobi/androidsdk/InterstitialView;)Z
    //   425: ifeq +62 -> 487
    //   428: invokestatic 44	java/lang/System:currentTimeMillis	()J
    //   431: lstore 4
    //   433: aload_2
    //   434: invokestatic 220	com/inmobi/androidsdk/InterstitialView:j	(Lcom/inmobi/androidsdk/InterstitialView;)J
    //   437: lstore 6
    //   439: new 54	org/json/JSONObject
    //   442: dup
    //   443: invokespecial 55	org/json/JSONObject:<init>	()V
    //   446: astore_1
    //   447: aload_1
    //   448: ldc 57
    //   450: aload_2
    //   451: invokestatic 61	com/inmobi/androidsdk/InterstitialView:e	(Lcom/inmobi/androidsdk/InterstitialView;)Ljava/lang/String;
    //   454: invokevirtual 65	org/json/JSONObject:put	(Ljava/lang/String;Ljava/lang/Object;)Lorg/json/JSONObject;
    //   457: pop
    //   458: aload_1
    //   459: ldc 67
    //   461: lload 4
    //   463: lload 6
    //   465: lsub
    //   466: invokevirtual 70	org/json/JSONObject:put	(Ljava/lang/String;J)Lorg/json/JSONObject;
    //   469: pop
    //   470: invokestatic 76	com/inmobi/androidsdk/bootstrapper/Initializer:getLogger	()Lcom/inmobi/commons/metric/Logger;
    //   473: new 78	com/inmobi/commons/metric/EventLog
    //   476: dup
    //   477: getstatic 223	com/inmobi/androidsdk/bootstrapper/NetworkEventType:RENDER_TIMEOUT	Lcom/inmobi/androidsdk/bootstrapper/NetworkEventType;
    //   480: aload_1
    //   481: invokespecial 87	com/inmobi/commons/metric/EventLog:<init>	(Lcom/inmobi/commons/metric/EventType;Lorg/json/JSONObject;)V
    //   484: invokevirtual 93	com/inmobi/commons/metric/Logger:logEvent	(Lcom/inmobi/commons/metric/EventLog;)V
    //   487: aload_2
    //   488: bipush 101
    //   490: getstatic 226	com/inmobi/androidsdk/AdRequest$ErrorCode:AD_RENDERING_TIMEOUT	Lcom/inmobi/androidsdk/AdRequest$ErrorCode;
    //   493: invokestatic 191	com/inmobi/androidsdk/InterstitialView:a	(Lcom/inmobi/androidsdk/InterstitialView;ILcom/inmobi/androidsdk/AdRequest$ErrorCode;)V
    //   496: return
    //   497: astore_3
    //   498: ldc -91
    //   500: new 142	java/lang/StringBuilder
    //   503: dup
    //   504: ldc -58
    //   506: invokespecial 201	java/lang/StringBuilder:<init>	(Ljava/lang/String;)V
    //   509: invokestatic 44	java/lang/System:currentTimeMillis	()J
    //   512: invokevirtual 147	java/lang/StringBuilder:append	(J)Ljava/lang/StringBuilder;
    //   515: invokevirtual 151	java/lang/StringBuilder:toString	()Ljava/lang/String;
    //   518: invokestatic 204	com/inmobi/commons/internal/Log:internal	(Ljava/lang/String;Ljava/lang/String;)V
    //   521: goto -51 -> 470
    //   524: aload_0
    //   525: sipush 308
    //   528: invokevirtual 97	com/inmobi/androidsdk/InterstitialView$c:removeMessages	(I)V
    //   531: aload_0
    //   532: sipush 309
    //   535: invokevirtual 97	com/inmobi/androidsdk/InterstitialView$c:removeMessages	(I)V
    //   538: aload_2
    //   539: getstatic 179	com/inmobi/androidsdk/InterstitialView$State:INIT	Lcom/inmobi/androidsdk/InterstitialView$State;
    //   542: invokestatic 182	com/inmobi/androidsdk/InterstitialView:a	(Lcom/inmobi/androidsdk/InterstitialView;Lcom/inmobi/androidsdk/InterstitialView$State;)Lcom/inmobi/androidsdk/InterstitialView$State;
    //   545: pop
    //   546: invokestatic 44	java/lang/System:currentTimeMillis	()J
    //   549: lstore 4
    //   551: aload_2
    //   552: invokestatic 48	com/inmobi/androidsdk/InterstitialView:c	(Lcom/inmobi/androidsdk/InterstitialView;)J
    //   555: lstore 6
    //   557: aload_2
    //   558: invokestatic 52	com/inmobi/androidsdk/InterstitialView:d	(Lcom/inmobi/androidsdk/InterstitialView;)Z
    //   561: ifeq +48 -> 609
    //   564: new 54	org/json/JSONObject
    //   567: dup
    //   568: invokespecial 55	org/json/JSONObject:<init>	()V
    //   571: astore_1
    //   572: aload_1
    //   573: ldc 67
    //   575: lload 4
    //   577: lload 6
    //   579: lsub
    //   580: invokevirtual 70	org/json/JSONObject:put	(Ljava/lang/String;J)Lorg/json/JSONObject;
    //   583: pop
    //   584: aload_1
    //   585: ldc -28
    //   587: iconst_1
    //   588: invokevirtual 231	org/json/JSONObject:put	(Ljava/lang/String;I)Lorg/json/JSONObject;
    //   591: pop
    //   592: invokestatic 76	com/inmobi/androidsdk/bootstrapper/Initializer:getLogger	()Lcom/inmobi/commons/metric/Logger;
    //   595: new 78	com/inmobi/commons/metric/EventLog
    //   598: dup
    //   599: getstatic 234	com/inmobi/androidsdk/bootstrapper/NetworkEventType:CONNECT_ERROR	Lcom/inmobi/androidsdk/bootstrapper/NetworkEventType;
    //   602: aload_1
    //   603: invokespecial 87	com/inmobi/commons/metric/EventLog:<init>	(Lcom/inmobi/commons/metric/EventType;Lorg/json/JSONObject;)V
    //   606: invokevirtual 93	com/inmobi/commons/metric/Logger:logEvent	(Lcom/inmobi/commons/metric/EventLog;)V
    //   609: aload_2
    //   610: invokestatic 238	com/inmobi/androidsdk/InterstitialView:k	(Lcom/inmobi/androidsdk/InterstitialView;)Lcom/inmobi/androidsdk/impl/net/RequestResponseManager;
    //   613: invokevirtual 243	com/inmobi/androidsdk/impl/net/RequestResponseManager:doCancel	()V
    //   616: aload_2
    //   617: bipush 101
    //   619: getstatic 246	com/inmobi/androidsdk/AdRequest$ErrorCode:AD_FETCH_TIMEOUT	Lcom/inmobi/androidsdk/AdRequest$ErrorCode;
    //   622: invokestatic 191	com/inmobi/androidsdk/InterstitialView:a	(Lcom/inmobi/androidsdk/InterstitialView;ILcom/inmobi/androidsdk/AdRequest$ErrorCode;)V
    //   625: return
    //   626: astore_3
    //   627: ldc -91
    //   629: new 142	java/lang/StringBuilder
    //   632: dup
    //   633: ldc -8
    //   635: invokespecial 201	java/lang/StringBuilder:<init>	(Ljava/lang/String;)V
    //   638: invokestatic 44	java/lang/System:currentTimeMillis	()J
    //   641: invokevirtual 147	java/lang/StringBuilder:append	(J)Ljava/lang/StringBuilder;
    //   644: invokevirtual 151	java/lang/StringBuilder:toString	()Ljava/lang/String;
    //   647: invokestatic 204	com/inmobi/commons/internal/Log:internal	(Ljava/lang/String;Ljava/lang/String;)V
    //   650: goto -58 -> 592
    //   653: aload_2
    //   654: invokestatic 52	com/inmobi/androidsdk/InterstitialView:d	(Lcom/inmobi/androidsdk/InterstitialView;)Z
    //   657: ifeq +62 -> 719
    //   660: invokestatic 44	java/lang/System:currentTimeMillis	()J
    //   663: lstore 4
    //   665: aload_2
    //   666: invokestatic 220	com/inmobi/androidsdk/InterstitialView:j	(Lcom/inmobi/androidsdk/InterstitialView;)J
    //   669: lstore 6
    //   671: new 54	org/json/JSONObject
    //   674: dup
    //   675: invokespecial 55	org/json/JSONObject:<init>	()V
    //   678: astore_1
    //   679: aload_1
    //   680: ldc 57
    //   682: aload_2
    //   683: invokestatic 61	com/inmobi/androidsdk/InterstitialView:e	(Lcom/inmobi/androidsdk/InterstitialView;)Ljava/lang/String;
    //   686: invokevirtual 65	org/json/JSONObject:put	(Ljava/lang/String;Ljava/lang/Object;)Lorg/json/JSONObject;
    //   689: pop
    //   690: aload_1
    //   691: ldc 67
    //   693: lload 4
    //   695: lload 6
    //   697: lsub
    //   698: invokevirtual 70	org/json/JSONObject:put	(Ljava/lang/String;J)Lorg/json/JSONObject;
    //   701: pop
    //   702: invokestatic 76	com/inmobi/androidsdk/bootstrapper/Initializer:getLogger	()Lcom/inmobi/commons/metric/Logger;
    //   705: new 78	com/inmobi/commons/metric/EventLog
    //   708: dup
    //   709: getstatic 251	com/inmobi/androidsdk/bootstrapper/NetworkEventType:RENDER_COMPLETE	Lcom/inmobi/androidsdk/bootstrapper/NetworkEventType;
    //   712: aload_1
    //   713: invokespecial 87	com/inmobi/commons/metric/EventLog:<init>	(Lcom/inmobi/commons/metric/EventType;Lorg/json/JSONObject;)V
    //   716: invokevirtual 93	com/inmobi/commons/metric/Logger:logEvent	(Lcom/inmobi/commons/metric/EventLog;)V
    //   719: aload_0
    //   720: sipush 307
    //   723: invokevirtual 97	com/inmobi/androidsdk/InterstitialView$c:removeMessages	(I)V
    //   726: aload_2
    //   727: getstatic 254	com/inmobi/androidsdk/InterstitialView$State:READY	Lcom/inmobi/androidsdk/InterstitialView$State;
    //   730: invokestatic 182	com/inmobi/androidsdk/InterstitialView:a	(Lcom/inmobi/androidsdk/InterstitialView;Lcom/inmobi/androidsdk/InterstitialView$State;)Lcom/inmobi/androidsdk/InterstitialView$State;
    //   733: pop
    //   734: aload_2
    //   735: bipush 100
    //   737: aconst_null
    //   738: invokestatic 191	com/inmobi/androidsdk/InterstitialView:a	(Lcom/inmobi/androidsdk/InterstitialView;ILcom/inmobi/androidsdk/AdRequest$ErrorCode;)V
    //   741: return
    //   742: astore_3
    //   743: ldc -91
    //   745: new 142	java/lang/StringBuilder
    //   748: dup
    //   749: ldc_w 256
    //   752: invokespecial 201	java/lang/StringBuilder:<init>	(Ljava/lang/String;)V
    //   755: invokestatic 44	java/lang/System:currentTimeMillis	()J
    //   758: invokevirtual 147	java/lang/StringBuilder:append	(J)Ljava/lang/StringBuilder;
    //   761: invokevirtual 151	java/lang/StringBuilder:toString	()Ljava/lang/String;
    //   764: invokestatic 204	com/inmobi/commons/internal/Log:internal	(Ljava/lang/String;Ljava/lang/String;)V
    //   767: goto -65 -> 702
    //   770: aload_2
    //   771: getstatic 179	com/inmobi/androidsdk/InterstitialView$State:INIT	Lcom/inmobi/androidsdk/InterstitialView$State;
    //   774: invokestatic 182	com/inmobi/androidsdk/InterstitialView:a	(Lcom/inmobi/androidsdk/InterstitialView;Lcom/inmobi/androidsdk/InterstitialView$State;)Lcom/inmobi/androidsdk/InterstitialView$State;
    //   777: pop
    //   778: aload_2
    //   779: bipush 103
    //   781: aconst_null
    //   782: invokestatic 191	com/inmobi/androidsdk/InterstitialView:a	(Lcom/inmobi/androidsdk/InterstitialView;ILcom/inmobi/androidsdk/AdRequest$ErrorCode;)V
    //   785: aload_2
    //   786: aconst_null
    //   787: invokestatic 117	com/inmobi/androidsdk/InterstitialView:a	(Lcom/inmobi/androidsdk/InterstitialView;Lcom/inmobi/re/container/IMWebView;)Lcom/inmobi/re/container/IMWebView;
    //   790: pop
    //   791: return
    //   792: aload_2
    //   793: getstatic 259	com/inmobi/androidsdk/InterstitialView$State:ACTIVE	Lcom/inmobi/androidsdk/InterstitialView$State;
    //   796: invokestatic 182	com/inmobi/androidsdk/InterstitialView:a	(Lcom/inmobi/androidsdk/InterstitialView;Lcom/inmobi/androidsdk/InterstitialView$State;)Lcom/inmobi/androidsdk/InterstitialView$State;
    //   799: pop
    //   800: aload_2
    //   801: bipush 102
    //   803: aconst_null
    //   804: invokestatic 191	com/inmobi/androidsdk/InterstitialView:a	(Lcom/inmobi/androidsdk/InterstitialView;ILcom/inmobi/androidsdk/AdRequest$ErrorCode;)V
    //   807: return
    //   808: return
    // Local variable table:
    //   start	length	slot	name	signature
    //   0	809	0	this	c
    //   0	809	1	paramMessage	android.os.Message
    //   10	791	2	localInterstitialView	InterstitialView
    //   278	1	3	localJSONException1	org.json.JSONException
    //   497	1	3	localJSONException2	org.json.JSONException
    //   626	1	3	localJSONException3	org.json.JSONException
    //   742	1	3	localJSONException4	org.json.JSONException
    //   72	622	4	l1	long
    //   437	259	6	l2	long
    // Exception table:
    //   from	to	target	type
    //   133	176	241	java/lang/Exception
    //   176	196	241	java/lang/Exception
    //   196	232	241	java/lang/Exception
    //   232	240	241	java/lang/Exception
    //   15	64	268	java/lang/Exception
    //   64	89	268	java/lang/Exception
    //   89	109	268	java/lang/Exception
    //   109	126	268	java/lang/Exception
    //   126	133	268	java/lang/Exception
    //   242	267	268	java/lang/Exception
    //   279	302	268	java/lang/Exception
    //   305	333	268	java/lang/Exception
    //   334	371	268	java/lang/Exception
    //   372	447	268	java/lang/Exception
    //   447	470	268	java/lang/Exception
    //   470	487	268	java/lang/Exception
    //   487	496	268	java/lang/Exception
    //   498	521	268	java/lang/Exception
    //   524	572	268	java/lang/Exception
    //   572	592	268	java/lang/Exception
    //   592	609	268	java/lang/Exception
    //   609	625	268	java/lang/Exception
    //   627	650	268	java/lang/Exception
    //   653	679	268	java/lang/Exception
    //   679	702	268	java/lang/Exception
    //   702	719	268	java/lang/Exception
    //   719	741	268	java/lang/Exception
    //   743	767	268	java/lang/Exception
    //   770	791	268	java/lang/Exception
    //   792	807	268	java/lang/Exception
    //   89	109	278	org/json/JSONException
    //   447	470	497	org/json/JSONException
    //   572	592	626	org/json/JSONException
    //   679	702	742	org/json/JSONException
  }
}

/* Location:
 * Qualified Name:     com.inmobi.androidsdk.InterstitialView.c
 * Java Class Version: 6 (50.0)
 * JD-Core Version:    0.7.1
 */