package net.simonvt.menudrawer.a;

import android.widget.ImageView;
import java.lang.reflect.Method;

public final class c
{
  public ImageView a;
  public Object b;
  public Method c;
  
  /* Error */
  c(android.app.Activity paramActivity)
  {
    // Byte code:
    //   0: aload_0
    //   1: invokespecial 17	java/lang/Object:<init>	()V
    //   4: aload_1
    //   5: invokevirtual 23	android/app/Activity:getPackageName	()Ljava/lang/String;
    //   8: astore_2
    //   9: aload_0
    //   10: aload_1
    //   11: aload_1
    //   12: invokevirtual 27	android/app/Activity:getResources	()Landroid/content/res/Resources;
    //   15: ldc 29
    //   17: ldc 31
    //   19: aload_2
    //   20: invokevirtual 37	android/content/res/Resources:getIdentifier	(Ljava/lang/String;Ljava/lang/String;Ljava/lang/String;)I
    //   23: invokevirtual 41	android/app/Activity:findViewById	(I)Landroid/view/View;
    //   26: invokevirtual 47	android/view/View:getParent	()Landroid/view/ViewParent;
    //   29: checkcast 49	android/view/ViewGroup
    //   32: aload_1
    //   33: invokevirtual 27	android/app/Activity:getResources	()Landroid/content/res/Resources;
    //   36: ldc 51
    //   38: ldc 31
    //   40: aload_2
    //   41: invokevirtual 37	android/content/res/Resources:getIdentifier	(Ljava/lang/String;Ljava/lang/String;Ljava/lang/String;)I
    //   44: invokevirtual 52	android/view/ViewGroup:findViewById	(I)Landroid/view/View;
    //   47: checkcast 54	android/widget/ImageView
    //   50: putfield 56	net/simonvt/menudrawer/a/c:a	Landroid/widget/ImageView;
    //   53: aload_0
    //   54: getfield 56	net/simonvt/menudrawer/a/c:a	Landroid/widget/ImageView;
    //   57: ifnonnull +47 -> 104
    //   60: aload_0
    //   61: aload_1
    //   62: aload_1
    //   63: invokevirtual 27	android/app/Activity:getResources	()Landroid/content/res/Resources;
    //   66: ldc 58
    //   68: ldc 31
    //   70: aload_2
    //   71: invokevirtual 37	android/content/res/Resources:getIdentifier	(Ljava/lang/String;Ljava/lang/String;Ljava/lang/String;)I
    //   74: invokevirtual 41	android/app/Activity:findViewById	(I)Landroid/view/View;
    //   77: invokevirtual 47	android/view/View:getParent	()Landroid/view/ViewParent;
    //   80: checkcast 49	android/view/ViewGroup
    //   83: aload_1
    //   84: invokevirtual 27	android/app/Activity:getResources	()Landroid/content/res/Resources;
    //   87: ldc 60
    //   89: ldc 31
    //   91: aload_2
    //   92: invokevirtual 37	android/content/res/Resources:getIdentifier	(Ljava/lang/String;Ljava/lang/String;Ljava/lang/String;)I
    //   95: invokevirtual 52	android/view/ViewGroup:findViewById	(I)Landroid/view/View;
    //   98: checkcast 54	android/widget/ImageView
    //   101: putfield 56	net/simonvt/menudrawer/a/c:a	Landroid/widget/ImageView;
    //   104: aload_0
    //   105: aload_1
    //   106: invokevirtual 64	java/lang/Object:getClass	()Ljava/lang/Class;
    //   109: ldc 66
    //   111: iconst_0
    //   112: anewarray 68	java/lang/Class
    //   115: invokevirtual 72	java/lang/Class:getMethod	(Ljava/lang/String;[Ljava/lang/Class;)Ljava/lang/reflect/Method;
    //   118: aload_1
    //   119: aconst_null
    //   120: invokevirtual 78	java/lang/reflect/Method:invoke	(Ljava/lang/Object;[Ljava/lang/Object;)Ljava/lang/Object;
    //   123: putfield 80	net/simonvt/menudrawer/a/c:b	Ljava/lang/Object;
    //   126: aload_0
    //   127: aload_0
    //   128: getfield 80	net/simonvt/menudrawer/a/c:b	Ljava/lang/Object;
    //   131: invokevirtual 64	java/lang/Object:getClass	()Ljava/lang/Class;
    //   134: ldc 82
    //   136: iconst_1
    //   137: anewarray 68	java/lang/Class
    //   140: dup
    //   141: iconst_0
    //   142: getstatic 88	java/lang/Boolean:TYPE	Ljava/lang/Class;
    //   145: aastore
    //   146: invokevirtual 72	java/lang/Class:getMethod	(Ljava/lang/String;[Ljava/lang/Class;)Ljava/lang/reflect/Method;
    //   149: putfield 90	net/simonvt/menudrawer/a/c:c	Ljava/lang/reflect/Method;
    //   152: return
    //   153: astore_1
    //   154: return
    //   155: astore_3
    //   156: goto -103 -> 53
    // Local variable table:
    //   start	length	slot	name	signature
    //   0	159	0	this	c
    //   0	159	1	paramActivity	android.app.Activity
    //   8	84	2	str	String
    //   155	1	3	localThrowable	Throwable
    // Exception table:
    //   from	to	target	type
    //   4	9	153	java/lang/Throwable
    //   53	104	153	java/lang/Throwable
    //   104	152	153	java/lang/Throwable
    //   9	53	155	java/lang/Throwable
  }
}

/* Location:
 * Qualified Name:     net.simonvt.menudrawer.a.c
 * Java Class Version: 6 (50.0)
 * JD-Core Version:    0.7.1
 */