package com.millennialmedia.android;

import android.content.Context;

final class MRaid$1
  implements Runnable
{
  MRaid$1(String paramString, Context paramContext) {}
  
  /* Error */
  public final void run()
  {
    // Byte code:
    //   0: new 29	org/apache/http/client/methods/HttpGet
    //   3: dup
    //   4: aload_0
    //   5: getfield 14	com/millennialmedia/android/MRaid$1:val$url	Ljava/lang/String;
    //   8: invokespecial 32	org/apache/http/client/methods/HttpGet:<init>	(Ljava/lang/String;)V
    //   11: astore_1
    //   12: new 34	org/apache/http/impl/client/DefaultHttpClient
    //   15: dup
    //   16: invokespecial 35	org/apache/http/impl/client/DefaultHttpClient:<init>	()V
    //   19: aload_1
    //   20: invokevirtual 39	org/apache/http/impl/client/DefaultHttpClient:execute	(Lorg/apache/http/client/methods/HttpUriRequest;)Lorg/apache/http/HttpResponse;
    //   23: astore_1
    //   24: aload_0
    //   25: getfield 16	com/millennialmedia/android/MRaid$1:val$context	Landroid/content/Context;
    //   28: aload_1
    //   29: invokeinterface 45 1 0
    //   34: invokeinterface 51 1 0
    //   39: invokestatic 57	com/millennialmedia/android/MRaid:saveMRaid	(Landroid/content/Context;Ljava/io/InputStream;)Z
    //   42: ifeq +14 -> 56
    //   45: aload_0
    //   46: getfield 16	com/millennialmedia/android/MRaid$1:val$context	Landroid/content/Context;
    //   49: aload_0
    //   50: getfield 14	com/millennialmedia/android/MRaid$1:val$url	Ljava/lang/String;
    //   53: invokestatic 61	com/millennialmedia/android/MRaid:storeMraidUrl	(Landroid/content/Context;Ljava/lang/String;)V
    //   56: return
    //   57: astore_1
    //   58: aload_1
    //   59: invokevirtual 64	java/net/MalformedURLException:printStackTrace	()V
    //   62: return
    //   63: astore_1
    //   64: aload_1
    //   65: athrow
    //   66: astore_1
    //   67: aload_1
    //   68: invokevirtual 65	java/lang/IllegalStateException:printStackTrace	()V
    //   71: return
    //   72: astore_1
    //   73: aload_1
    //   74: invokevirtual 66	java/io/IOException:printStackTrace	()V
    //   77: return
    // Local variable table:
    //   start	length	slot	name	signature
    //   0	78	0	this	1
    //   11	18	1	localObject1	Object
    //   57	2	1	localMalformedURLException	java.net.MalformedURLException
    //   63	2	1	localObject2	Object
    //   66	2	1	localIllegalStateException	IllegalStateException
    //   72	2	1	localIOException	java.io.IOException
    // Exception table:
    //   from	to	target	type
    //   0	56	57	java/net/MalformedURLException
    //   0	56	63	finally
    //   58	62	63	finally
    //   67	71	63	finally
    //   73	77	63	finally
    //   0	56	66	java/lang/IllegalStateException
    //   0	56	72	java/io/IOException
  }
}

/* Location:
 * Qualified Name:     com.millennialmedia.android.MRaid.1
 * Java Class Version: 6 (50.0)
 * JD-Core Version:    0.7.1
 */