package com.admob.android.ads;

class AdMobLocalizer$InitLocalizerThread
  extends Thread
{
  final AdMobLocalizer this$0;
  
  private AdMobLocalizer$InitLocalizerThread(AdMobLocalizer paramAdMobLocalizer) {}
  
  AdMobLocalizer$InitLocalizerThread(AdMobLocalizer paramAdMobLocalizer, AdMobLocalizer.1 param1)
  {
    this(paramAdMobLocalizer);
  }
  
  /* Error */
  public void run()
  {
    // Byte code:
    //   0: nop
    //   1: new 117	java/lang/StringBuilder
    //   4: astore 8
    //   6: aload 8
    //   8: invokespecial 38	java/lang/StringBuilder:<init>	()V
    //   11: invokestatic 107	com/admob/android/ads/AdMobLocalizer:access$100	()Ljava/lang/String;
    //   14: astore 12
    //   16: aload 8
    //   18: aload 12
    //   20: invokevirtual 57	java/lang/StringBuilder:append	(Ljava/lang/String;)Ljava/lang/StringBuilder;
    //   23: pop
    //   24: ldc 92
    //   26: astore 12
    //   28: aload 8
    //   30: aload 12
    //   32: invokevirtual 57	java/lang/StringBuilder:append	(Ljava/lang/String;)Ljava/lang/StringBuilder;
    //   35: pop
    //   36: aload_0
    //   37: getfield 108	com/admob/android/ads/AdMobLocalizer$InitLocalizerThread:this$0	Lcom/admob/android/ads/AdMobLocalizer;
    //   40: astore 12
    //   42: aload 12
    //   44: invokestatic 93	com/admob/android/ads/AdMobLocalizer:access$200	(Lcom/admob/android/ads/AdMobLocalizer;)Ljava/lang/String;
    //   47: astore 12
    //   49: aload 8
    //   51: aload 12
    //   53: invokevirtual 57	java/lang/StringBuilder:append	(Ljava/lang/String;)Ljava/lang/StringBuilder;
    //   56: pop
    //   57: invokestatic 42	com/admob/android/ads/AdMobLocalizer:access$300	()Ljava/lang/String;
    //   60: astore 12
    //   62: aload 8
    //   64: aload 12
    //   66: invokevirtual 57	java/lang/StringBuilder:append	(Ljava/lang/String;)Ljava/lang/StringBuilder;
    //   69: pop
    //   70: new 80	java/net/URL
    //   73: astore 9
    //   75: aload 8
    //   77: invokevirtual 129	java/lang/StringBuilder:toString	()Ljava/lang/String;
    //   80: astore 12
    //   82: aload 9
    //   84: aload 12
    //   86: invokespecial 130	java/net/URL:<init>	(Ljava/lang/String;)V
    //   89: aload 9
    //   91: invokevirtual 31	java/net/URL:openConnection	()Ljava/net/URLConnection;
    //   94: astore 10
    //   96: aload 10
    //   98: invokevirtual 81	java/net/URLConnection:connect	()V
    //   101: new 124	java/io/BufferedInputStream
    //   104: astore 5
    //   106: aload 10
    //   108: invokevirtual 109	java/net/URLConnection:getInputStream	()Ljava/io/InputStream;
    //   111: astore 12
    //   113: aload 5
    //   115: aload 12
    //   117: invokespecial 122	java/io/BufferedInputStream:<init>	(Ljava/io/InputStream;)V
    //   120: aload_0
    //   121: getfield 108	com/admob/android/ads/AdMobLocalizer$InitLocalizerThread:this$0	Lcom/admob/android/ads/AdMobLocalizer;
    //   124: astore 12
    //   126: aload 12
    //   128: invokestatic 16	com/admob/android/ads/AdMobLocalizer:access$500	(Lcom/admob/android/ads/AdMobLocalizer;)Landroid/content/Context;
    //   131: astore 12
    //   133: invokestatic 77	com/admob/android/ads/AdMobLocalizer:access$400	()Ljava/lang/String;
    //   136: astore 13
    //   138: iconst_0
    //   139: istore 14
    //   141: aload 12
    //   143: aload 13
    //   145: iload 14
    //   147: invokevirtual 131	android/content/Context:getDir	(Ljava/lang/String;I)Ljava/io/File;
    //   150: astore_3
    //   151: new 91	java/io/File
    //   154: astore 11
    //   156: ldc 17
    //   158: astore 12
    //   160: aload 11
    //   162: aload_3
    //   163: aload 12
    //   165: invokespecial 5	java/io/File:<init>	(Ljava/io/File;Ljava/lang/String;)V
    //   168: aload 11
    //   170: invokevirtual 127	java/io/File:exists	()Z
    //   173: istore 12
    //   175: iload 12
    //   177: ifne +9 -> 186
    //   180: aload 11
    //   182: invokevirtual 102	java/io/File:mkdir	()Z
    //   185: pop
    //   186: new 91	java/io/File
    //   189: astore 7
    //   191: new 117	java/lang/StringBuilder
    //   194: astore 12
    //   196: aload 12
    //   198: invokespecial 38	java/lang/StringBuilder:<init>	()V
    //   201: aload_0
    //   202: getfield 108	com/admob/android/ads/AdMobLocalizer$InitLocalizerThread:this$0	Lcom/admob/android/ads/AdMobLocalizer;
    //   205: astore 13
    //   207: aload 13
    //   209: invokestatic 93	com/admob/android/ads/AdMobLocalizer:access$200	(Lcom/admob/android/ads/AdMobLocalizer;)Ljava/lang/String;
    //   212: astore 13
    //   214: aload 12
    //   216: aload 13
    //   218: invokevirtual 57	java/lang/StringBuilder:append	(Ljava/lang/String;)Ljava/lang/StringBuilder;
    //   221: astore 12
    //   223: invokestatic 42	com/admob/android/ads/AdMobLocalizer:access$300	()Ljava/lang/String;
    //   226: astore 13
    //   228: aload 12
    //   230: aload 13
    //   232: invokevirtual 57	java/lang/StringBuilder:append	(Ljava/lang/String;)Ljava/lang/StringBuilder;
    //   235: astore 12
    //   237: aload 12
    //   239: invokevirtual 129	java/lang/StringBuilder:toString	()Ljava/lang/String;
    //   242: astore 12
    //   244: aload 7
    //   246: aload 11
    //   248: aload 12
    //   250: invokespecial 5	java/io/File:<init>	(Ljava/io/File;Ljava/lang/String;)V
    //   253: new 65	java/io/BufferedOutputStream
    //   256: astore 6
    //   258: new 105	java/io/FileOutputStream
    //   261: astore 12
    //   263: aload 12
    //   265: aload 7
    //   267: invokespecial 89	java/io/FileOutputStream:<init>	(Ljava/io/File;)V
    //   270: aload 6
    //   272: aload 12
    //   274: invokespecial 83	java/io/BufferedOutputStream:<init>	(Ljava/io/OutputStream;)V
    //   277: sipush 512
    //   280: istore 12
    //   282: iload 12
    //   284: newarray <illegal type>
    //   286: astore_1
    //   287: iconst_0
    //   288: istore_2
    //   289: iconst_0
    //   290: istore 12
    //   292: aload_1
    //   293: arraylength
    //   294: istore 13
    //   296: aload 5
    //   298: aload_1
    //   299: iload 12
    //   301: iload 13
    //   303: invokevirtual 3	java/io/BufferedInputStream:read	([BII)I
    //   306: istore_2
    //   307: iload_2
    //   308: ifle +72 -> 380
    //   311: iconst_0
    //   312: istore 12
    //   314: aload 6
    //   316: aload_1
    //   317: iload 12
    //   319: iload_2
    //   320: invokevirtual 72	java/io/BufferedOutputStream:write	([BII)V
    //   323: goto -34 -> 289
    //   326: astore 12
    //   328: aload 6
    //   330: invokevirtual 52	java/io/BufferedOutputStream:close	()V
    //   333: aload 12
    //   335: athrow
    //   336: astore 12
    //   338: aload 12
    //   340: astore 4
    //   342: ldc 97
    //   344: astore 12
    //   346: iconst_3
    //   347: istore 13
    //   349: aload 12
    //   351: iload 13
    //   353: invokestatic 94	android/util/Log:isLoggable	(Ljava/lang/String;I)Z
    //   356: istore 12
    //   358: iload 12
    //   360: ifeq +19 -> 379
    //   363: ldc 97
    //   365: astore 12
    //   367: ldc 99
    //   369: astore 13
    //   371: aload 12
    //   373: aload 13
    //   375: invokestatic 100	android/util/Log:d	(Ljava/lang/String;Ljava/lang/String;)I
    //   378: pop
    //   379: return
    //   380: aload 6
    //   382: invokevirtual 52	java/io/BufferedOutputStream:close	()V
    //   385: goto -6 -> 379
    //   388: nop
    // Local variable table:
    //   start	length	slot	name	signature
    //   0	389	0	this	InitLocalizerThread
    //   286	31	1	arrayOfByte	byte[]
    //   288	32	2	i	int
    //   150	13	3	localFile1	java.io.File
    //   340	1	4	localException1	Exception
    //   104	193	5	localBufferedInputStream	java.io.BufferedInputStream
    //   256	125	6	localBufferedOutputStream	java.io.BufferedOutputStream
    //   189	77	7	localFile2	java.io.File
    //   4	72	8	localStringBuilder	StringBuilder
    //   73	17	9	localURL	java.net.URL
    //   94	13	10	localURLConnection	java.net.URLConnection
    //   154	93	11	localFile3	java.io.File
    //   14	150	12	localObject1	Object
    //   173	3	12	bool1	boolean
    //   194	79	12	localObject2	Object
    //   280	38	12	j	int
    //   326	8	12	localObject3	Object
    //   336	3	12	localException2	Exception
    //   344	6	12	str1	String
    //   356	3	12	bool2	boolean
    //   365	7	12	str2	String
    //   136	95	13	localObject4	Object
    //   294	58	13	k	int
    //   369	5	13	str3	String
    //   139	7	14	m	int
    // Exception table:
    //   from	to	target	type
    //   282	287	326	finally
    //   292	296	326	finally
    //   314	323	326	finally
    //   70	75	336	java/lang/Exception
    //   82	89	336	java/lang/Exception
    //   96	101	336	java/lang/Exception
    //   106	111	336	java/lang/Exception
    //   113	120	336	java/lang/Exception
    //   126	131	336	java/lang/Exception
    //   133	136	336	java/lang/Exception
    //   141	150	336	java/lang/Exception
    //   151	156	336	java/lang/Exception
    //   160	168	336	java/lang/Exception
    //   180	186	336	java/lang/Exception
    //   191	196	336	java/lang/Exception
    //   201	207	336	java/lang/Exception
    //   214	221	336	java/lang/Exception
    //   223	226	336	java/lang/Exception
    //   228	235	336	java/lang/Exception
    //   237	242	336	java/lang/Exception
    //   244	253	336	java/lang/Exception
    //   258	263	336	java/lang/Exception
    //   270	277	336	java/lang/Exception
    //   328	333	336	java/lang/Exception
    //   380	385	336	java/lang/Exception
  }
}

/* Location:
 * Qualified Name:     com.admob.android.ads.AdMobLocalizer.InitLocalizerThread
 * Java Class Version: 1.2 (46.0)
 * JD-Core Version:    0.7.1
 */