package com.appyet.activity;

import android.content.Context;
import android.widget.ArrayAdapter;
import com.mobeta.android.dslv.DragSortListView;

public final class b
  extends ArrayAdapter<c>
{
  private Context b;
  
  public b(CustomizeActivity paramCustomizeActivity, Context paramContext)
  {
    super(paramContext, 0);
    b = paramContext;
  }
  
  public final int getItemViewType(int paramInt)
  {
    if (a.g.getItemAtPosition(paramInt)).f) {
      return 0;
    }
    return 1;
  }
  
  /* Error */
  public final android.view.View getView(int paramInt, android.view.View paramView, android.view.ViewGroup paramViewGroup)
  {
    // Byte code:
    //   0: aconst_null
    //   1: astore 5
    //   3: aconst_null
    //   4: astore 4
    //   6: aload_0
    //   7: iload_1
    //   8: invokevirtual 46	com/appyet/activity/b:getItem	(I)Ljava/lang/Object;
    //   11: checkcast 35	com/appyet/activity/c
    //   14: astore 7
    //   16: aload_2
    //   17: ifnonnull +286 -> 303
    //   20: aload 7
    //   22: getfield 39	com/appyet/activity/c:f	Z
    //   25: ifeq +199 -> 224
    //   28: aload_0
    //   29: invokevirtual 50	com/appyet/activity/b:getContext	()Landroid/content/Context;
    //   32: invokestatic 56	android/view/LayoutInflater:from	(Landroid/content/Context;)Landroid/view/LayoutInflater;
    //   35: ldc 57
    //   37: aconst_null
    //   38: invokevirtual 61	android/view/LayoutInflater:inflate	(ILandroid/view/ViewGroup;)Landroid/view/View;
    //   41: astore_2
    //   42: new 63	com/appyet/activity/e
    //   45: dup
    //   46: invokespecial 66	com/appyet/activity/e:<init>	()V
    //   49: astore_3
    //   50: aload_3
    //   51: aload_2
    //   52: ldc 67
    //   54: invokevirtual 73	android/view/View:findViewById	(I)Landroid/view/View;
    //   57: checkcast 75	android/widget/TextView
    //   60: putfield 78	com/appyet/activity/e:b	Landroid/widget/TextView;
    //   63: aload_3
    //   64: aload_2
    //   65: ldc 79
    //   67: invokevirtual 73	android/view/View:findViewById	(I)Landroid/view/View;
    //   70: putfield 83	com/appyet/activity/e:c	Landroid/view/View;
    //   73: aload_2
    //   74: aload_3
    //   75: invokevirtual 87	android/view/View:setTag	(Ljava/lang/Object;)V
    //   78: aload 7
    //   80: getfield 39	com/appyet/activity/c:f	Z
    //   83: ifne +103 -> 186
    //   86: aload_3
    //   87: getfield 90	com/appyet/activity/e:a	Landroid/widget/ImageView;
    //   90: ifnull +88 -> 178
    //   93: aload 7
    //   95: getfield 94	com/appyet/activity/c:e	Ljava/lang/String;
    //   98: ifnull +289 -> 387
    //   101: aload_0
    //   102: getfield 13	com/appyet/activity/b:a	Lcom/appyet/activity/CustomizeActivity;
    //   105: invokevirtual 98	com/appyet/activity/CustomizeActivity:getResources	()Landroid/content/res/Resources;
    //   108: invokevirtual 104	android/content/res/Resources:getAssets	()Landroid/content/res/AssetManager;
    //   111: new 106	java/lang/StringBuilder
    //   114: dup
    //   115: ldc 108
    //   117: invokespecial 111	java/lang/StringBuilder:<init>	(Ljava/lang/String;)V
    //   120: aload 7
    //   122: getfield 94	com/appyet/activity/c:e	Ljava/lang/String;
    //   125: invokevirtual 115	java/lang/StringBuilder:append	(Ljava/lang/String;)Ljava/lang/StringBuilder;
    //   128: invokevirtual 119	java/lang/StringBuilder:toString	()Ljava/lang/String;
    //   131: invokevirtual 125	android/content/res/AssetManager:open	(Ljava/lang/String;)Ljava/io/InputStream;
    //   134: astore 6
    //   136: aload 6
    //   138: astore 4
    //   140: aload 6
    //   142: astore 5
    //   144: aload 6
    //   146: invokestatic 131	android/graphics/BitmapFactory:decodeStream	(Ljava/io/InputStream;)Landroid/graphics/Bitmap;
    //   149: astore 8
    //   151: aload 6
    //   153: astore 4
    //   155: aload 6
    //   157: astore 5
    //   159: aload_3
    //   160: getfield 90	com/appyet/activity/e:a	Landroid/widget/ImageView;
    //   163: aload 8
    //   165: invokevirtual 137	android/widget/ImageView:setImageBitmap	(Landroid/graphics/Bitmap;)V
    //   168: aload 6
    //   170: ifnull +8 -> 178
    //   173: aload 6
    //   175: invokevirtual 142	java/io/InputStream:close	()V
    //   178: aload_3
    //   179: getfield 83	com/appyet/activity/e:c	Landroid/view/View;
    //   182: iconst_0
    //   183: invokevirtual 146	android/view/View:setVisibility	(I)V
    //   186: aload_3
    //   187: getfield 78	com/appyet/activity/e:b	Landroid/widget/TextView;
    //   190: aload_0
    //   191: getfield 13	com/appyet/activity/b:a	Lcom/appyet/activity/CustomizeActivity;
    //   194: aload 7
    //   196: getfield 148	com/appyet/activity/c:a	Ljava/lang/String;
    //   199: invokestatic 153	com/appyet/f/w:b	(Landroid/content/Context;Ljava/lang/String;)Ljava/lang/String;
    //   202: invokevirtual 157	android/widget/TextView:setText	(Ljava/lang/CharSequence;)V
    //   205: aload 7
    //   207: getfield 159	com/appyet/activity/c:g	Z
    //   210: ifeq +12 -> 222
    //   213: aload_3
    //   214: getfield 83	com/appyet/activity/e:c	Landroid/view/View;
    //   217: bipush 8
    //   219: invokevirtual 146	android/view/View:setVisibility	(I)V
    //   222: aload_2
    //   223: areturn
    //   224: aload_0
    //   225: invokevirtual 50	com/appyet/activity/b:getContext	()Landroid/content/Context;
    //   228: invokestatic 56	android/view/LayoutInflater:from	(Landroid/content/Context;)Landroid/view/LayoutInflater;
    //   231: ldc -96
    //   233: aconst_null
    //   234: invokevirtual 61	android/view/LayoutInflater:inflate	(ILandroid/view/ViewGroup;)Landroid/view/View;
    //   237: astore_2
    //   238: new 63	com/appyet/activity/e
    //   241: dup
    //   242: invokespecial 66	com/appyet/activity/e:<init>	()V
    //   245: astore_3
    //   246: aload_3
    //   247: aload_2
    //   248: ldc -95
    //   250: invokevirtual 73	android/view/View:findViewById	(I)Landroid/view/View;
    //   253: checkcast 163	android/widget/RelativeLayout
    //   256: putfield 167	com/appyet/activity/e:d	Landroid/widget/RelativeLayout;
    //   259: aload_3
    //   260: aload_2
    //   261: ldc 67
    //   263: invokevirtual 73	android/view/View:findViewById	(I)Landroid/view/View;
    //   266: checkcast 75	android/widget/TextView
    //   269: putfield 78	com/appyet/activity/e:b	Landroid/widget/TextView;
    //   272: aload_3
    //   273: aload_2
    //   274: ldc 79
    //   276: invokevirtual 73	android/view/View:findViewById	(I)Landroid/view/View;
    //   279: putfield 83	com/appyet/activity/e:c	Landroid/view/View;
    //   282: aload_3
    //   283: aload_2
    //   284: ldc -88
    //   286: invokevirtual 73	android/view/View:findViewById	(I)Landroid/view/View;
    //   289: checkcast 133	android/widget/ImageView
    //   292: putfield 90	com/appyet/activity/e:a	Landroid/widget/ImageView;
    //   295: aload_2
    //   296: aload_3
    //   297: invokevirtual 87	android/view/View:setTag	(Ljava/lang/Object;)V
    //   300: goto -222 -> 78
    //   303: aload_2
    //   304: invokevirtual 172	android/view/View:getTag	()Ljava/lang/Object;
    //   307: checkcast 63	com/appyet/activity/e
    //   310: astore_3
    //   311: goto -233 -> 78
    //   314: astore 6
    //   316: aload 4
    //   318: astore 5
    //   320: aload 6
    //   322: invokestatic 177	com/appyet/d/d:a	(Ljava/lang/Exception;)V
    //   325: aload 4
    //   327: astore 5
    //   329: aload_3
    //   330: getfield 90	com/appyet/activity/e:a	Landroid/widget/ImageView;
    //   333: ldc -78
    //   335: invokevirtual 181	android/widget/ImageView:setImageResource	(I)V
    //   338: aload 4
    //   340: ifnull -162 -> 178
    //   343: aload 4
    //   345: invokevirtual 142	java/io/InputStream:close	()V
    //   348: goto -170 -> 178
    //   351: astore 4
    //   353: aload 4
    //   355: invokestatic 177	com/appyet/d/d:a	(Ljava/lang/Exception;)V
    //   358: aload_3
    //   359: getfield 90	com/appyet/activity/e:a	Landroid/widget/ImageView;
    //   362: astore 4
    //   364: aload 4
    //   366: ldc -78
    //   368: invokevirtual 181	android/widget/ImageView:setImageResource	(I)V
    //   371: goto -193 -> 178
    //   374: astore_2
    //   375: aload 5
    //   377: ifnull +8 -> 385
    //   380: aload 5
    //   382: invokevirtual 142	java/io/InputStream:close	()V
    //   385: aload_2
    //   386: athrow
    //   387: aload_3
    //   388: getfield 90	com/appyet/activity/e:a	Landroid/widget/ImageView;
    //   391: ldc -78
    //   393: invokevirtual 181	android/widget/ImageView:setImageResource	(I)V
    //   396: goto -218 -> 178
    //   399: astore 4
    //   401: aload 4
    //   403: invokestatic 177	com/appyet/d/d:a	(Ljava/lang/Exception;)V
    //   406: aload_3
    //   407: getfield 90	com/appyet/activity/e:a	Landroid/widget/ImageView;
    //   410: ldc -78
    //   412: invokevirtual 181	android/widget/ImageView:setImageResource	(I)V
    //   415: goto -30 -> 385
    //   418: astore 4
    //   420: aload 4
    //   422: invokestatic 177	com/appyet/d/d:a	(Ljava/lang/Exception;)V
    //   425: aload_3
    //   426: getfield 90	com/appyet/activity/e:a	Landroid/widget/ImageView;
    //   429: astore 4
    //   431: goto -67 -> 364
    // Local variable table:
    //   start	length	slot	name	signature
    //   0	434	0	this	b
    //   0	434	1	paramInt	int
    //   0	434	2	paramView	android.view.View
    //   0	434	3	paramViewGroup	android.view.ViewGroup
    //   4	340	4	localObject1	Object
    //   351	3	4	localIOException1	java.io.IOException
    //   362	3	4	localImageView1	android.widget.ImageView
    //   399	3	4	localIOException2	java.io.IOException
    //   418	3	4	localIOException3	java.io.IOException
    //   429	1	4	localImageView2	android.widget.ImageView
    //   1	380	5	localObject2	Object
    //   134	40	6	localInputStream	java.io.InputStream
    //   314	7	6	localIOException4	java.io.IOException
    //   14	192	7	localc	c
    //   149	15	8	localBitmap	android.graphics.Bitmap
    // Exception table:
    //   from	to	target	type
    //   101	136	314	java/io/IOException
    //   144	151	314	java/io/IOException
    //   159	168	314	java/io/IOException
    //   343	348	351	java/io/IOException
    //   101	136	374	finally
    //   144	151	374	finally
    //   159	168	374	finally
    //   320	325	374	finally
    //   329	338	374	finally
    //   380	385	399	java/io/IOException
    //   173	178	418	java/io/IOException
  }
  
  public final int getViewTypeCount()
  {
    return 2;
  }
  
  public final boolean isEnabled(int paramInt)
  {
    return !a.g.getItemAtPosition(paramInt)).f;
  }
}

/* Location:
 * Qualified Name:     com.appyet.activity.b
 * Java Class Version: 6 (50.0)
 * JD-Core Version:    0.7.1
 */