package com.inmobi.androidsdk.impl.net;

import com.inmobi.androidsdk.impl.UserInfo;

class RequestResponseManager$c
  extends Thread
{
  RequestResponseManager$c(RequestResponseManager paramRequestResponseManager, UserInfo paramUserInfo, String paramString, RequestResponseManager.ActionType paramActionType, HttpRequestCallback paramHttpRequestCallback) {}
  
  /* Error */
  public void run()
  {
    // Byte code:
    //   0: aconst_null
    //   1: astore_1
    //   2: aload_0
    //   3: getfield 20	com/inmobi/androidsdk/impl/net/RequestResponseManager$c:a	Lcom/inmobi/androidsdk/impl/UserInfo;
    //   6: invokevirtual 43	com/inmobi/androidsdk/impl/UserInfo:getApplicationContext	()Landroid/content/Context;
    //   9: invokestatic 49	com/inmobi/commons/thinICE/icedatacollector/IceDataCollector:getConnectedWifiInfo	(Landroid/content/Context;)Lcom/inmobi/commons/thinICE/wifi/WifiInfo;
    //   12: astore_2
    //   13: aload_2
    //   14: astore_1
    //   15: ldc 51
    //   17: new 53	java/lang/StringBuilder
    //   20: dup
    //   21: ldc 55
    //   23: invokespecial 58	java/lang/StringBuilder:<init>	(Ljava/lang/String;)V
    //   26: aload_0
    //   27: getfield 22	com/inmobi/androidsdk/impl/net/RequestResponseManager$c:b	Ljava/lang/String;
    //   30: invokevirtual 62	java/lang/StringBuilder:append	(Ljava/lang/String;)Ljava/lang/StringBuilder;
    //   33: invokevirtual 66	java/lang/StringBuilder:toString	()Ljava/lang/String;
    //   36: invokestatic 72	com/inmobi/commons/internal/Log:internal	(Ljava/lang/String;Ljava/lang/String;)V
    //   39: aload_0
    //   40: getfield 20	com/inmobi/androidsdk/impl/net/RequestResponseManager$c:a	Lcom/inmobi/androidsdk/impl/UserInfo;
    //   43: aload_1
    //   44: aload_0
    //   45: getfield 24	com/inmobi/androidsdk/impl/net/RequestResponseManager$c:c	Lcom/inmobi/androidsdk/impl/net/RequestResponseManager$ActionType;
    //   48: invokestatic 78	com/inmobi/androidsdk/impl/net/HttpRequestBuilder:buildPostBody	(Lcom/inmobi/androidsdk/impl/UserInfo;Lcom/inmobi/commons/thinICE/wifi/WifiInfo;Lcom/inmobi/androidsdk/impl/net/RequestResponseManager$ActionType;)Ljava/lang/String;
    //   51: astore_1
    //   52: ldc 51
    //   54: new 53	java/lang/StringBuilder
    //   57: dup
    //   58: ldc 80
    //   60: invokespecial 58	java/lang/StringBuilder:<init>	(Ljava/lang/String;)V
    //   63: aload_1
    //   64: invokevirtual 62	java/lang/StringBuilder:append	(Ljava/lang/String;)Ljava/lang/StringBuilder;
    //   67: invokevirtual 66	java/lang/StringBuilder:toString	()Ljava/lang/String;
    //   70: invokestatic 72	com/inmobi/commons/internal/Log:internal	(Ljava/lang/String;Ljava/lang/String;)V
    //   73: aload_0
    //   74: getfield 18	com/inmobi/androidsdk/impl/net/RequestResponseManager$c:e	Lcom/inmobi/androidsdk/impl/net/RequestResponseManager;
    //   77: aload_1
    //   78: aload_0
    //   79: getfield 26	com/inmobi/androidsdk/impl/net/RequestResponseManager$c:d	Lcom/inmobi/androidsdk/impl/net/HttpRequestCallback;
    //   82: invokestatic 85	com/inmobi/androidsdk/impl/net/RequestResponseManager:a	(Lcom/inmobi/androidsdk/impl/net/RequestResponseManager;Ljava/lang/String;Lcom/inmobi/androidsdk/impl/net/HttpRequestCallback;)Ljava/lang/String;
    //   85: astore_1
    //   86: aload_0
    //   87: getfield 18	com/inmobi/androidsdk/impl/net/RequestResponseManager$c:e	Lcom/inmobi/androidsdk/impl/net/RequestResponseManager;
    //   90: aload_0
    //   91: getfield 18	com/inmobi/androidsdk/impl/net/RequestResponseManager$c:e	Lcom/inmobi/androidsdk/impl/net/RequestResponseManager;
    //   94: aload_0
    //   95: getfield 22	com/inmobi/androidsdk/impl/net/RequestResponseManager$c:b	Ljava/lang/String;
    //   98: aload_0
    //   99: getfield 20	com/inmobi/androidsdk/impl/net/RequestResponseManager$c:a	Lcom/inmobi/androidsdk/impl/UserInfo;
    //   102: invokestatic 88	com/inmobi/androidsdk/impl/net/RequestResponseManager:a	(Lcom/inmobi/androidsdk/impl/net/RequestResponseManager;Ljava/lang/String;Lcom/inmobi/androidsdk/impl/UserInfo;)Ljava/net/HttpURLConnection;
    //   105: invokestatic 91	com/inmobi/androidsdk/impl/net/RequestResponseManager:a	(Lcom/inmobi/androidsdk/impl/net/RequestResponseManager;Ljava/net/HttpURLConnection;)Ljava/net/HttpURLConnection;
    //   108: pop
    //   109: aload_1
    //   110: ifnull +92 -> 202
    //   113: ldc 51
    //   115: new 53	java/lang/StringBuilder
    //   118: dup
    //   119: ldc 93
    //   121: invokespecial 58	java/lang/StringBuilder:<init>	(Ljava/lang/String;)V
    //   124: aload_1
    //   125: invokevirtual 62	java/lang/StringBuilder:append	(Ljava/lang/String;)Ljava/lang/StringBuilder;
    //   128: invokevirtual 66	java/lang/StringBuilder:toString	()Ljava/lang/String;
    //   131: invokestatic 96	com/inmobi/commons/internal/Log:debug	(Ljava/lang/String;Ljava/lang/String;)V
    //   134: aload_0
    //   135: getfield 18	com/inmobi/androidsdk/impl/net/RequestResponseManager$c:e	Lcom/inmobi/androidsdk/impl/net/RequestResponseManager;
    //   138: aload_1
    //   139: invokestatic 99	com/inmobi/androidsdk/impl/net/RequestResponseManager:a	(Lcom/inmobi/androidsdk/impl/net/RequestResponseManager;Ljava/lang/String;)V
    //   142: aload_0
    //   143: getfield 18	com/inmobi/androidsdk/impl/net/RequestResponseManager$c:e	Lcom/inmobi/androidsdk/impl/net/RequestResponseManager;
    //   146: aload_0
    //   147: getfield 20	com/inmobi/androidsdk/impl/net/RequestResponseManager$c:a	Lcom/inmobi/androidsdk/impl/UserInfo;
    //   150: invokestatic 102	com/inmobi/androidsdk/impl/net/RequestResponseManager:a	(Lcom/inmobi/androidsdk/impl/net/RequestResponseManager;Lcom/inmobi/androidsdk/impl/UserInfo;)Lcom/inmobi/androidsdk/impl/net/Response;
    //   153: astore_1
    //   154: aload_0
    //   155: getfield 18	com/inmobi/androidsdk/impl/net/RequestResponseManager$c:e	Lcom/inmobi/androidsdk/impl/net/RequestResponseManager;
    //   158: iconst_0
    //   159: aload_1
    //   160: aload_0
    //   161: getfield 26	com/inmobi/androidsdk/impl/net/RequestResponseManager$c:d	Lcom/inmobi/androidsdk/impl/net/HttpRequestCallback;
    //   164: invokestatic 105	com/inmobi/androidsdk/impl/net/RequestResponseManager:a	(Lcom/inmobi/androidsdk/impl/net/RequestResponseManager;ILjava/lang/Object;Lcom/inmobi/androidsdk/impl/net/HttpRequestCallback;)V
    //   167: return
    //   168: astore_2
    //   169: ldc 51
    //   171: ldc 107
    //   173: invokestatic 72	com/inmobi/commons/internal/Log:internal	(Ljava/lang/String;Ljava/lang/String;)V
    //   176: goto -161 -> 15
    //   179: astore_1
    //   180: ldc 51
    //   182: ldc 109
    //   184: aload_1
    //   185: invokestatic 112	com/inmobi/commons/internal/Log:debug	(Ljava/lang/String;Ljava/lang/String;Ljava/lang/Throwable;)V
    //   188: aload_0
    //   189: getfield 18	com/inmobi/androidsdk/impl/net/RequestResponseManager$c:e	Lcom/inmobi/androidsdk/impl/net/RequestResponseManager;
    //   192: iconst_1
    //   193: aload_1
    //   194: aload_0
    //   195: getfield 26	com/inmobi/androidsdk/impl/net/RequestResponseManager$c:d	Lcom/inmobi/androidsdk/impl/net/HttpRequestCallback;
    //   198: invokestatic 105	com/inmobi/androidsdk/impl/net/RequestResponseManager:a	(Lcom/inmobi/androidsdk/impl/net/RequestResponseManager;ILjava/lang/Object;Lcom/inmobi/androidsdk/impl/net/HttpRequestCallback;)V
    //   201: return
    //   202: aload_0
    //   203: getfield 18	com/inmobi/androidsdk/impl/net/RequestResponseManager$c:e	Lcom/inmobi/androidsdk/impl/net/RequestResponseManager;
    //   206: iconst_1
    //   207: getstatic 118	com/inmobi/androidsdk/AdRequest$ErrorCode:INTERNAL_ERROR	Lcom/inmobi/androidsdk/AdRequest$ErrorCode;
    //   210: aload_0
    //   211: getfield 26	com/inmobi/androidsdk/impl/net/RequestResponseManager$c:d	Lcom/inmobi/androidsdk/impl/net/HttpRequestCallback;
    //   214: invokestatic 105	com/inmobi/androidsdk/impl/net/RequestResponseManager:a	(Lcom/inmobi/androidsdk/impl/net/RequestResponseManager;ILjava/lang/Object;Lcom/inmobi/androidsdk/impl/net/HttpRequestCallback;)V
    //   217: return
    //   218: astore_1
    //   219: ldc 51
    //   221: ldc 109
    //   223: aload_1
    //   224: invokestatic 112	com/inmobi/commons/internal/Log:debug	(Ljava/lang/String;Ljava/lang/String;Ljava/lang/Throwable;)V
    //   227: aload_1
    //   228: instanceof 120
    //   231: ifeq +26 -> 257
    //   234: ldc 51
    //   236: ldc 122
    //   238: invokestatic 72	com/inmobi/commons/internal/Log:internal	(Ljava/lang/String;Ljava/lang/String;)V
    //   241: aload_0
    //   242: getfield 18	com/inmobi/androidsdk/impl/net/RequestResponseManager$c:e	Lcom/inmobi/androidsdk/impl/net/RequestResponseManager;
    //   245: iconst_1
    //   246: getstatic 125	com/inmobi/androidsdk/AdRequest$ErrorCode:AD_FETCH_TIMEOUT	Lcom/inmobi/androidsdk/AdRequest$ErrorCode;
    //   249: aload_0
    //   250: getfield 26	com/inmobi/androidsdk/impl/net/RequestResponseManager$c:d	Lcom/inmobi/androidsdk/impl/net/HttpRequestCallback;
    //   253: invokestatic 105	com/inmobi/androidsdk/impl/net/RequestResponseManager:a	(Lcom/inmobi/androidsdk/impl/net/RequestResponseManager;ILjava/lang/Object;Lcom/inmobi/androidsdk/impl/net/HttpRequestCallback;)V
    //   256: return
    //   257: aload_0
    //   258: getfield 18	com/inmobi/androidsdk/impl/net/RequestResponseManager$c:e	Lcom/inmobi/androidsdk/impl/net/RequestResponseManager;
    //   261: iconst_1
    //   262: getstatic 128	com/inmobi/androidsdk/AdRequest$ErrorCode:NETWORK_ERROR	Lcom/inmobi/androidsdk/AdRequest$ErrorCode;
    //   265: aload_0
    //   266: getfield 26	com/inmobi/androidsdk/impl/net/RequestResponseManager$c:d	Lcom/inmobi/androidsdk/impl/net/HttpRequestCallback;
    //   269: invokestatic 105	com/inmobi/androidsdk/impl/net/RequestResponseManager:a	(Lcom/inmobi/androidsdk/impl/net/RequestResponseManager;ILjava/lang/Object;Lcom/inmobi/androidsdk/impl/net/HttpRequestCallback;)V
    //   272: return
    //   273: astore_1
    //   274: ldc 51
    //   276: ldc 109
    //   278: aload_1
    //   279: invokestatic 112	com/inmobi/commons/internal/Log:debug	(Ljava/lang/String;Ljava/lang/String;Ljava/lang/Throwable;)V
    //   282: aload_0
    //   283: getfield 18	com/inmobi/androidsdk/impl/net/RequestResponseManager$c:e	Lcom/inmobi/androidsdk/impl/net/RequestResponseManager;
    //   286: iconst_1
    //   287: getstatic 118	com/inmobi/androidsdk/AdRequest$ErrorCode:INTERNAL_ERROR	Lcom/inmobi/androidsdk/AdRequest$ErrorCode;
    //   290: aload_0
    //   291: getfield 26	com/inmobi/androidsdk/impl/net/RequestResponseManager$c:d	Lcom/inmobi/androidsdk/impl/net/HttpRequestCallback;
    //   294: invokestatic 105	com/inmobi/androidsdk/impl/net/RequestResponseManager:a	(Lcom/inmobi/androidsdk/impl/net/RequestResponseManager;ILjava/lang/Object;Lcom/inmobi/androidsdk/impl/net/HttpRequestCallback;)V
    //   297: return
    // Local variable table:
    //   start	length	slot	name	signature
    //   0	298	0	this	c
    //   1	159	1	localObject	Object
    //   179	15	1	localAdException	com.inmobi.androidsdk.impl.AdException
    //   218	10	1	localIOException	java.io.IOException
    //   273	6	1	localException1	Exception
    //   12	2	2	localWifiInfo	com.inmobi.commons.thinICE.wifi.WifiInfo
    //   168	1	2	localException2	Exception
    // Exception table:
    //   from	to	target	type
    //   2	13	168	java/lang/Exception
    //   2	13	179	com/inmobi/androidsdk/impl/AdException
    //   15	109	179	com/inmobi/androidsdk/impl/AdException
    //   113	167	179	com/inmobi/androidsdk/impl/AdException
    //   169	176	179	com/inmobi/androidsdk/impl/AdException
    //   202	217	179	com/inmobi/androidsdk/impl/AdException
    //   2	13	218	java/io/IOException
    //   15	109	218	java/io/IOException
    //   113	167	218	java/io/IOException
    //   169	176	218	java/io/IOException
    //   202	217	218	java/io/IOException
    //   15	109	273	java/lang/Exception
    //   113	167	273	java/lang/Exception
    //   169	176	273	java/lang/Exception
    //   202	217	273	java/lang/Exception
  }
}

/* Location:
 * Qualified Name:     com.inmobi.androidsdk.impl.net.RequestResponseManager.c
 * Java Class Version: 6 (50.0)
 * JD-Core Version:    0.7.1
 */